case_alignment_package/__init__.py
alignllm_case_alignment_package-0.1.3.dist-info/METADATA
alignllm_case_alignment_package-0.1.3.dist-info/WHEEL
alignllm_case_alignment_package-0.1.3.dist-info/top_level.txt
alignllm_case_alignment_package-0.1.3.dist-info/RECORD
