Metadata-Version: 2.4
Name: alignllm_case_alignment_package
Version: 0.1.3
Summary: A package for computing case alignment using embeddings - AlignLLM
Author: Ramitha Abeyratne
Requires-Python: >=3.8
Requires-Dist: numpy
Requires-Dist: scikit-learn
